sji/__init__.py
sji/sji.py
sji-0.4.0.dist-info/licenses/LICENSE
sji-0.4.0.dist-info/METADATA
sji-0.4.0.dist-info/WHEEL
sji-0.4.0.dist-info/top_level.txt
sji-0.4.0.dist-info/RECORD
