Metadata-Version: 2.4
Name: sji
Version: 0.4.0
Summary: SJI - Eine einfache Python-Bibliothek für Job-Initialisierung
Home-page: https://github.com/matzek92/simple-job-init
Author: matzek92
Author-email: matzek92 <your.email@example.com>
Project-URL: Homepage, https://github.com/matzek92/simple-job-init
Project-URL: Repository, https://github.com/matzek92/simple-job-init.git
Keywords: job,task,simple
Classifier: Development Status :: 3 - Alpha
Classifier: Intended Audience :: Developers
Classifier: License :: OSI Approved :: MIT License
Classifier: Operating System :: OS Independent
Classifier: Programming Language :: Python :: 3
Classifier: Programming Language :: Python :: 3.8
Classifier: Programming Language :: Python :: 3.9
Classifier: Programming Language :: Python :: 3.10
Classifier: Programming Language :: Python :: 3.11
Classifier: Programming Language :: Python :: 3.12
Requires-Python: >=3.8
License-File: LICENSE
Dynamic: author
Dynamic: home-page
Dynamic: license-file
Dynamic: requires-python
